{"errors":[],"warnings":[],"namedChunkGroups":{"app":{"chunks":[6,1,0,2],"assets":["webpack-runtime-f7558a62de0200dd35c7.js","webpack-runtime-f7558a62de0200dd35c7.js.map","styles.3065301360e73d0b0b16.css","styles-13b8eac80f92fe80753a.js","styles-13b8eac80f92fe80753a.js.map","commons-a927d3c08e2ec562361d.js","commons-a927d3c08e2ec562361d.js.map","app-eb235afa667f2bec57cb.js","app-eb235afa667f2bec57cb.js.map"],"children":{},"childAssets":{}},"component---src-templates-page-tsx":{"chunks":[1,0,5],"assets":["styles.3065301360e73d0b0b16.css","styles-13b8eac80f92fe80753a.js","styles-13b8eac80f92fe80753a.js.map","commons-a927d3c08e2ec562361d.js","commons-a927d3c08e2ec562361d.js.map","component---src-templates-page-tsx-eb4d74a8309a2531448d.js","component---src-templates-page-tsx-eb4d74a8309a2531448d.js.map"],"children":{},"childAssets":{}},"component---src-pages-404-tsx":{"chunks":[1,0,3],"assets":["styles.3065301360e73d0b0b16.css","styles-13b8eac80f92fe80753a.js","styles-13b8eac80f92fe80753a.js.map","commons-a927d3c08e2ec562361d.js","commons-a927d3c08e2ec562361d.js.map","component---src-pages-404-tsx-6a936a0703be0dbcf4aa.js","component---src-pages-404-tsx-6a936a0703be0dbcf4aa.js.map"],"children":{},"childAssets":{}},"component---src-pages-index-tsx":{"chunks":[1,0,4],"assets":["styles.3065301360e73d0b0b16.css","styles-13b8eac80f92fe80753a.js","styles-13b8eac80f92fe80753a.js.map","commons-a927d3c08e2ec562361d.js","commons-a927d3c08e2ec562361d.js.map","component---src-pages-index-tsx-37d6cb92f3c00774456a.js","component---src-pages-index-tsx-37d6cb92f3c00774456a.js.map"],"children":{},"childAssets":{}}},"assetsByChunkName":{"app":["webpack-runtime-f7558a62de0200dd35c7.js","styles.3065301360e73d0b0b16.css","styles-13b8eac80f92fe80753a.js","commons-a927d3c08e2ec562361d.js","app-eb235afa667f2bec57cb.js"],"component---src-templates-page-tsx":["styles.3065301360e73d0b0b16.css","styles-13b8eac80f92fe80753a.js","commons-a927d3c08e2ec562361d.js","component---src-templates-page-tsx-eb4d74a8309a2531448d.js"],"component---src-pages-404-tsx":["styles.3065301360e73d0b0b16.css","styles-13b8eac80f92fe80753a.js","commons-a927d3c08e2ec562361d.js","component---src-pages-404-tsx-6a936a0703be0dbcf4aa.js"],"component---src-pages-index-tsx":["styles.3065301360e73d0b0b16.css","styles-13b8eac80f92fe80753a.js","commons-a927d3c08e2ec562361d.js","component---src-pages-index-tsx-37d6cb92f3c00774456a.js"]}}